kount_access/__init__.py
kount_access/access_sdk.py
kount_access_sdk-2.1.1.dist-info/DESCRIPTION.rst
kount_access_sdk-2.1.1.dist-info/METADATA
kount_access_sdk-2.1.1.dist-info/RECORD
kount_access_sdk-2.1.1.dist-info/WHEEL
kount_access_sdk-2.1.1.dist-info/metadata.json
kount_access_sdk-2.1.1.dist-info/top_level.txt
tests/__init__.py
tests/test_access.py
tests/test_access_mock.py
tests/test_params.py
