Metadata-Version: 2.0
Name: kount-access-sdk
Version: 2.1.1
Summary: Kount Python Access SDK
Home-page: https://github.com/Kount/kount-access-python-sdk
Author: Kount
Author-email: sdkadmin@kount.com
License: Kount
Keywords: kount,sdk,access
Platform: UNKNOWN
Classifier: Development Status :: 4 - Beta
Classifier: Intended Audience :: Developers
Classifier: Topic :: Software Development :: Build Tools
Classifier: Topic :: Internet :: WWW/HTTP
Classifier: Topic :: Software Development :: Libraries :: Python Modules
Classifier: License :: Other/Proprietary License
Classifier: Programming Language :: Python :: 2.7
Classifier: Programming Language :: Python :: 3.5
Classifier: Programming Language :: Python :: 3.6
Requires-Dist: requests (>=2.11.1)
